ez_pdf_tables/__init__.py
ez_pdf_tables/constants.py
ez_pdf_tables/multiindex.py
ez_pdf_tables/resources.py
ez_pdf_tables/tables.py
ez_pdf_tables-1.0.3.dist-info/LICENSE
ez_pdf_tables-1.0.3.dist-info/METADATA
ez_pdf_tables-1.0.3.dist-info/WHEEL
ez_pdf_tables-1.0.3.dist-info/RECORD
