Metadata-Version: 2.1
Name: ez-pdf-tables
Version: 1.0.3
Summary: Quickly make PDF tables.
Home-page: https://github.com/michaeleveringham/ez_pdf_tables
License: MIT
Author: Michael Everingham
Author-email: lamerlink@live.com
Requires-Python: >=3.7.1,<4.0.0
Classifier: Development Status :: 5 - Production/Stable
Classifier: License :: OSI Approved :: GNU General Public License v3 (GPLv3)
Classifier: License :: OSI Approved :: MIT License
Classifier: Operating System :: OS Independent
Classifier: Programming Language :: Python :: 3
Classifier: Programming Language :: Python :: 3.8
Classifier: Programming Language :: Python :: 3.9
Classifier: Programming Language :: Python :: 3.10
Classifier: Programming Language :: Python :: 3.11
Classifier: Typing :: Typed
Requires-Dist: pandas (>=1.3.2,<2.0.0)
Requires-Dist: reportlab (>=3.6.6,<4.0.0)
